{
  "annotations": {
    "list": [
      {
        "builtIn": 1,
        "datasource": "-- Grafana --",
        "enable": true,
        "hide": true,
        "iconColor": "rgba(0, 211, 255, 1)",
        "name": "Annotations \u0026 Alerts",
        "target": {
          "limit": 100,
          "matchAny": false,
          "tags": [],
          "type": "dashboard"
        },
        "type": "dashboard"
      }
    ]
  },
  "editable": true,
  "gnetId": null,
  "graphTooltip": 0,
  "links": [],
  "panels": [
    {
      "circleMaxSize": 30,
      "circleMinSize": 2,
      "colors": [
        "rgba(245, 54, 54, 0.9)",
        "rgba(237, 129, 40, 0.89)",
        "rgba(50, 172, 45, 0.97)"
      ],
      "datasource": null,
      "decimals": 0,
      "esMetric": "Count",
      "gridPos": {
        "h": 8,
        "w": 12,
        "x": 0,
        "y": 0
      },
      "hideEmpty": false,
      "hideZero": false,
      "id": 7,
      "initialZoom": "6",
      "locationData": "countries",
      "mapCenter": "Europe",
      "mapCenterLatitude": 46,
      "mapCenterLongitude": 14,
      "maxDataPoints": 1,
      "mouseWheelZoom": true,
      "showLegend": true,
      "stickyLabels": false,
      "tableQueryOptions": {
        "geohashField": "geohash",
        "latitudeField": "latitude",
        "longitudeField": "longitude",
        "metricField": "metric",
        "queryType": "geohash"
      },
      "thresholds": "0,10",
      "title": "Panel Title",
      "type": "grafana-worldmap-panel",
      "unitPlural": "",
      "unitSingle": "",
      "valueName": "total"
    },
    {
      "datasource": null,
      "fieldConfig": {
        "defaults": {
          "color": {
            "mode": "thresholds"
          },
          "mappings": [],
          "thresholds": {
            "mode": "absolute",
            "steps": [
              {
                "color": "green",
                "value": null
              },
              {
                "color": "red",
                "value": 80
              }
            ]
          }
        },
        "overrides": []
      },
      "gridPos": {
        "h": 10,
        "w": 10,
        "x": 0,
        "y": 8
      },
      "id": 2,
      "options": {
        "basemap": {
          "type": "stamen-terrain"
        },
        "controls": {
          "showAttribution": true,
          "showDebug": false,
          "showScale": false,
          "showZoom": true
        },
        "counters": {
          "dataChanged": true,
          "render": true,
          "schemaChanged": true
        },
        "mode": "render",
        "showZoomControl": true,
        "view": {
          "center": {
            "id": "zero"
          },
          "shared": true,
          "zoom": 1
        }
      },
      "title": "Panel Title",
      "type": "geomap"
    },
    {
      "datasource": null,
      "fieldConfig": {
        "defaults": {
          "color": {
            "mode": "palette-classic"
          },
          "custom": {
            "axisLabel": "",
            "axisPlacement": "auto",
            "barAlignment": 0,
            "drawStyle": "line",
            "fillOpacity": 0,
            "gradientMode": "none",
            "hideFrom": {
              "legend": false,
              "tooltip": false,
              "viz": false
            },
            "lineInterpolation": "linear",
            "lineWidth": 1,
            "pointSize": 5,
            "scaleDistribution": {
              "type": "linear"
            },
            "showPoints": "auto",
            "spanNulls": false,
            "stacking": {
              "group": "A",
              "mode": "none"
            },
            "thresholdsStyle": {
              "mode": "off"
            }
          },
          "mappings": [],
          "thresholds": {
            "mode": "absolute",
            "steps": [
              {
                "color": "green",
                "value": null
              },
              {
                "color": "red",
                "value": 80
              }
            ]
          }
        },
        "overrides": []
      },
      "gridPos": {
        "h": 10,
        "w": 11,
        "x": 10,
        "y": 8
      },
      "id": 4,
      "options": {
        "legend": {
          "calcs": [],
          "displayMode": "list",
          "placement": "bottom"
        },
        "tooltip": {
          "mode": "single"
        }
      },
      "title": "Panel Title",
      "type": "timeseries"
    },
    {
      "datasource": null,
      "fieldConfig": {
        "defaults": {
          "color": {
            "mode": "thresholds"
          },
          "mappings": [],
          "thresholds": {
            "mode": "absolute",
            "steps": [
              {
                "color": "green",
                "value": null
              },
              {
                "color": "red",
                "value": 80
              }
            ]
          }
        },
        "overrides": []
      },
      "gridPos": {
        "h": 10,
        "w": 10,
        "x": 0,
        "y": 18
      },
      "id": 5,
      "options": {
        "basemap": {
          "type": "esri-World_Physical_Map"
        },
        "controls": {
          "showAttribution": true,
          "showDebug": false,
          "showScale": false,
          "showZoom": true
        },
        "counters": {
          "dataChanged": true,
          "render": true,
          "schemaChanged": true
        },
        "mode": "render",
        "showZoomControl": true,
        "view": {
          "center": {
            "id": "zero"
          },
          "shared": true,
          "zoom": 1
        }
      },
      "title": "Panel Title",
      "type": "geomap"
    }
  ],
  "schemaVersion": 30,
  "style": "dark",
  "tags": [],
  "templating": {
    "list": []
  },
  "time": {
    "from": "now-6h",
    "to": "now"
  },
  "timepicker": {},
  "timezone": "",
  "title": "geomap"
}